{
  "org": "buildkite",
  "scanned_at": "2026-03-27T05:52:23Z",
  "repos": {
    "total": 221,
    "with_workflows": 11,
    "archived_skipped": 61,
    "forked_skipped": 26
  },
  "references": {
    "total": 84,
    "sha_pinned": 1,
    "tag_pinned": 82,
    "branch_pinned": 1
  },
  "unique_actions": [
    {
      "repo": "actions/checkout",
      "used_in_repos": 9,
      "refs": [
        {
          "ref": "v4",
          "type": "tag",
          "count": 13
        },
        {
          "ref": "v2",
          "type": "tag",
          "count": 8
        },
        {
          "ref": "v3",
          "type": "tag",
          "count": 4
        },
        {
          "ref": "v6",
          "type": "tag",
          "count": 4
        },
        {
          "ref": "v3.3.0",
          "type": "tag",
          "count": 1
        }
      ],
      "immutable_releases": false,
      "risk": "medium"
    },
    {
      "repo": "mcncl/trigger-pipeline-action",
      "used_in_repos": 1,
      "refs": [
        {
          "ref": "master",
          "type": "branch",
          "count": 1
        }
      ],
      "immutable_releases": null,
      "risk": "high"
    },
    {
      "repo": "actions/upload-artifact",
      "used_in_repos": 1,
      "refs": [
        {
          "ref": "v4",
          "type": "tag",
          "count": 4
        }
      ],
      "immutable_releases": false,
      "risk": "medium"
    },
    {
      "repo": "docker/setup-buildx-action",
      "used_in_repos": 1,
      "refs": [
        {
          "ref": "v3",
          "type": "tag",
          "count": 6
        }
      ],
      "immutable_releases": false,
      "risk": "medium"
    },
    {
      "repo": "docker/login-action",
      "used_in_repos": 1,
      "refs": [
        {
          "ref": "v3",
          "type": "tag",
          "count": 6
        }
      ],
      "immutable_releases": false,
      "risk": "medium"
    },
    {
      "repo": "reviewdog/action-yamllint",
      "used_in_repos": 1,
      "refs": [
        {
          "ref": "v1.6.1",
          "type": "tag",
          "count": 1
        }
      ],
      "immutable_releases": false,
      "risk": "medium"
    },
    {
      "repo": "actions/setup-dotnet",
      "used_in_repos": 1,
      "refs": [
        {
          "ref": "v5",
          "type": "tag",
          "count": 1
        }
      ],
      "immutable_releases": false,
      "risk": "medium"
    },
    {
      "repo": "astral-sh/setup-uv",
      "used_in_repos": 1,
      "refs": [
        {
          "ref": "v7",
          "type": "tag",
          "count": 2
        }
      ],
      "immutable_releases": false,
      "risk": "medium"
    },
    {
      "repo": "actions/cache",
      "used_in_repos": 1,
      "refs": [
        {
          "ref": "v4",
          "type": "tag",
          "count": 6
        }
      ],
      "immutable_releases": false,
      "risk": "medium"
    },
    {
      "repo": "reactivecircus/android-emulator-runner",
      "used_in_repos": 1,
      "refs": [
        {
          "ref": "v2.27.0",
          "type": "tag",
          "count": 1
        }
      ],
      "immutable_releases": false,
      "risk": "medium"
    },
    {
      "repo": "actions/upload-release-asset",
      "used_in_repos": 1,
      "refs": [
        {
          "ref": "v1",
          "type": "tag",
          "count": 2
        }
      ],
      "immutable_releases": false,
      "risk": "medium"
    },
    {
      "repo": "docker/build-push-action",
      "used_in_repos": 1,
      "refs": [
        {
          "ref": "v6",
          "type": "tag",
          "count": 3
        }
      ],
      "immutable_releases": true,
      "risk": "low"
    },
    {
      "repo": "goreleaser/goreleaser-action",
      "used_in_repos": 1,
      "refs": [
        {
          "ref": "v6",
          "type": "tag",
          "count": 1
        }
      ],
      "immutable_releases": false,
      "risk": "medium"
    },
    {
      "repo": "actions/labeler",
      "used_in_repos": 1,
      "refs": [
        {
          "ref": "634933edcd8ababfe52f92936142cc22ac488b1b",
          "type": "sha",
          "count": 1
        }
      ],
      "immutable_releases": false,
      "risk": "medium"
    },
    {
      "repo": "actions/create-release",
      "used_in_repos": 1,
      "refs": [
        {
          "ref": "v1",
          "type": "tag",
          "count": 1
        }
      ],
      "immutable_releases": false,
      "risk": "medium"
    },
    {
      "repo": "addnab/docker-run-action",
      "used_in_repos": 1,
      "refs": [
        {
          "ref": "v3",
          "type": "tag",
          "count": 1
        }
      ],
      "immutable_releases": false,
      "risk": "medium"
    },
    {
      "repo": "actions/download-artifact",
      "used_in_repos": 1,
      "refs": [
        {
          "ref": "v4",
          "type": "tag",
          "count": 5
        }
      ],
      "immutable_releases": false,
      "risk": "medium"
    },
    {
      "repo": "actions/setup-go",
      "used_in_repos": 1,
      "refs": [
        {
          "ref": "v5",
          "type": "tag",
          "count": 1
        }
      ],
      "immutable_releases": false,
      "risk": "medium"
    },
    {
      "repo": "actions/setup-java",
      "used_in_repos": 1,
      "refs": [
        {
          "ref": "v4",
          "type": "tag",
          "count": 4
        },
        {
          "ref": "v3.3.0",
          "type": "tag",
          "count": 1
        }
      ],
      "immutable_releases": false,
      "risk": "medium"
    },
    {
      "repo": "erlef/setup-beam",
      "used_in_repos": 1,
      "refs": [
        {
          "ref": "v1",
          "type": "tag",
          "count": 6
        }
      ],
      "immutable_releases": false,
      "risk": "medium"
    }
  ],
  "dangerous_triggers": [
    {
      "repo": "docs",
      "workflow_file": "labeler.yml",
      "trigger": "pull_request_target",
      "risk": "medium",
      "reason": "pull_request_target trigger requires manual review — grants write token on external PRs"
    }
  ],
  "org_policy": {
    "sha_pinning_required": false,
    "checked": false
  }
}
